app/__init__.py
app/batch/__init__.py
app/batch/predict.py
app/online/__init__.py
app/online/flask_app.py
epam_mle_model_deployment-1.0.dist-info/METADATA
epam_mle_model_deployment-1.0.dist-info/WHEEL
epam_mle_model_deployment-1.0.dist-info/top_level.txt
epam_mle_model_deployment-1.0.dist-info/RECORD
